shapes/__init__.py
shapes/car.py
shapes/circle.py
shapes/rectangle.py
turtledrawing/__init__.py
turtledrawing/car.py
turtledrawing/circle.py
turtledrawing/rectangle.py
turtledrawing-5.0.4.dist-info/METADATA
turtledrawing-5.0.4.dist-info/WHEEL
turtledrawing-5.0.4.dist-info/entry_points.txt
turtledrawing-5.0.4.dist-info/top_level.txt
turtledrawing-5.0.4.dist-info/RECORD
