Metadata-Version: 2.1
Name: turtledrawing
Version: 5.0.4
Summary: Draw Shapes with the Turtle Module.
Home-page: https://github.com/NotOrca22/learning-turtle
Author: orcawhale38
Author-email: orcawhale2008@gmail.com
License: MIT
Platform: UNKNOWN
Classifier: License :: OSI Approved :: MIT License
Classifier: Programming Language :: Python :: 3
Classifier: Programming Language :: Python :: 3.8
